stega/__init__.py
stega/__main__.py
stega/cli/__init__.py
stega/cli/command.py
stega/cli/textimg.py
stega/image/__init__.py
stega/image/text.py
stega_saurus_py-0.0.1a5.dist-info/LICENSE
stega_saurus_py-0.0.1a5.dist-info/METADATA
stega_saurus_py-0.0.1a5.dist-info/WHEEL
stega_saurus_py-0.0.1a5.dist-info/top_level.txt
stega_saurus_py-0.0.1a5.dist-info/RECORD
