Metadata-Version: 2.1
Name: stega-saurus-py
Version: 0.0.1a5
Summary: A steganography CLI
Home-page: https://github.com/gregmallan/stega-saurus
Author: Greg Allan
Author-email: gregallandev@gmail.com
License: UNKNOWN
Project-URL: Bug Tracker, https://github.com/gregmallan/stega-saurus/issues
Platform: UNKNOWN
Classifier: Development Status :: 3 - Alpha
Classifier: License :: OSI Approved :: GNU General Public License v3 (GPLv3)
Classifier: Natural Language :: English
Classifier: Operating System :: MacOS :: MacOS X
Classifier: Operating System :: POSIX :: Linux
Classifier: Programming Language :: Python
Classifier: Programming Language :: Python :: 3
Classifier: Programming Language :: Python :: 3 :: Only
Classifier: Programming Language :: Python :: 3.7
Classifier: Programming Language :: Python :: 3.8
Classifier: Programming Language :: Python :: 3.9
Classifier: Programming Language :: Python :: 3.10
Requires-Python: >=3.7.2
Requires-Dist: Pillow (<9.2,>=9.1.1)
Requires-Dist: typer (<0.5,>=0.4.1)
Provides-Extra: dev
Requires-Dist: pytest (<7.2,>=7.1.2) ; extra == 'dev'
Requires-Dist: pytest-cov (<3.1,>=3.0.0) ; extra == 'dev'
